certbot_dns_hydra/__init__.py
certbot_dns_hydra/certbot_dns_hydra.py
certbot_dns_hydra-0.2.1.dist-info/LICENSE
certbot_dns_hydra-0.2.1.dist-info/METADATA
certbot_dns_hydra-0.2.1.dist-info/WHEEL
certbot_dns_hydra-0.2.1.dist-info/entry_points.txt
certbot_dns_hydra-0.2.1.dist-info/top_level.txt
certbot_dns_hydra-0.2.1.dist-info/RECORD
