Metadata-Version: 2.2
Name: certbot-dns-hydra
Version: 0.2.1
Summary: Certbot plugin for Oxford Hydra DNS API
Author-email: Jonathan Young <jonathan.young@glam.ox.ac.uk>
License:                                  Apache License
Requires-Python: >=3.6
License-File: LICENSE
Requires-Dist: certbot>=1.0.0
Requires-Dist: requests
Requires-Dist: zope.interface
